cao/__init__.py
cao/shell/__init__.py
cao/shell/usage.py
cao/src/temp.txt
package_name/__init__.py
package_name/shell/__init__.py
package_name/shell/usage.py
package_name/src/temp.txt
cao-0.0.1.dist-info/LICENSE
cao-0.0.1.dist-info/METADATA
cao-0.0.1.dist-info/WHEEL
cao-0.0.1.dist-info/entry_points.txt
cao-0.0.1.dist-info/top_level.txt
cao-0.0.1.dist-info/zip-safe
cao-0.0.1.dist-info/RECORD
